data_linter/__init__.py
data_linter/command_line.py
data_linter/constants.py
data_linter/iam.py
data_linter/log_explorer_utils.py
data_linter/logging_functions.py
data_linter/schemas/config-schema.json
data_linter/utils.py
data_linter/validation.py
data_linter/validators/__init__.py
data_linter/validators/base.py
data_linter/validators/pandas_validator.py
data_linter/validators/parquet_validator.py
data_linter-6.3.2.dist-info/METADATA
data_linter-6.3.2.dist-info/WHEEL
data_linter-6.3.2.dist-info/entry_points.txt
data_linter-6.3.2.dist-info/RECORD
