Metadata-Version: 2.3
Name: data_linter
Version: 6.3.2
Summary: data linter
Author: Thomas Hirsch
Author-email: thomas.hirsch@digital.justice.gov.uk
Requires-Python: >=3.9,<4.0
Classifier: Programming Language :: Python :: 3
Classifier: Programming Language :: Python :: 3.9
Classifier: Programming Language :: Python :: 3.10
Classifier: Programming Language :: Python :: 3.11
Classifier: Programming Language :: Python :: 3.12
Classifier: Programming Language :: Python :: 3.13
Provides-Extra: frictionless
Provides-Extra: ge
Requires-Dist: PyYAML (>=6.0.1,<7.0.0)
Requires-Dist: arrow-pd-parser (>=1.3.0)
Requires-Dist: awswrangler (>=2.12.0)
Requires-Dist: boto3 (>=1.14.7,<2.0.0)
Requires-Dist: dataengineeringutils3 (>=1.0.1,<2.0.0)
Requires-Dist: iam_builder (>=4.1.0,<5.0.0)
Requires-Dist: jsonschema (>=4.10.0,<5.0.0)
Requires-Dist: mojap-metadata[arrow] (>=1.10.0,<2.0.0)
Requires-Dist: numpy (<2.0.0)
Requires-Dist: pandas (>=1.2)
Requires-Dist: setuptools (>=76.0.0)
Requires-Dist: toml (>=0.10,<0.11)
Project-URL: Homepage, https://github.com/moj-analytical-services/data_linter
Project-URL: Repository, https://github.com/moj-analytical-services/data_linter
